llm_quiver/__init__.py
llm_quiver/cache_manager.py
llm_quiver/io_util.py
llm_quiver/llm_quiver.py
llm_quiver/prompt_template_parser.py
llm_quiver/support_api.py
llm_quiver/wrap_openai.py
llm_quiver/prompt/prompt_template_parser.py
llm_quiver-0.3.8.dist-info/METADATA
llm_quiver-0.3.8.dist-info/WHEEL
llm_quiver-0.3.8.dist-info/licenses/LICENSE
llm_quiver-0.3.8.dist-info/RECORD
