Metadata-Version: 2.4
Name: llm-quiver
Version: 0.3.8
Summary: The auxiliary tool is used to invoke the online LLM service API, supporting local caching, prompt rendering, and configuration management.
Author-email: xrandx <kevtyle@hotmail.com>
License-File: LICENSE
Requires-Python: ~=3.8
Requires-Dist: loguru<0.8,>=0.7.0
Requires-Dist: openai<2,>=1.28.0
Requires-Dist: pyyaml<7,>=6.0.2
Requires-Dist: tiktoken==0.7.0
Requires-Dist: toml<0.11,>=0.10.2
Requires-Dist: tqdm<5,>=4.66.0
